nexport/__init__.py
nexport/calculators.py
nexport/colors.py
nexport/generic.py
nexport/models.py
nexport/utils.py
nexport/pytorch/__init__.py
nexport/pytorch/activation.py
nexport/pytorch/exporting.py
nexport/pytorch/importing.py
nexport/tensorflow/__init__.py
nexport/tensorflow/exporting.py
nexport/tensorflow/importing.py
nexport-0.4.6.dist-info/LICENSE.md
nexport-0.4.6.dist-info/METADATA
nexport-0.4.6.dist-info/WHEEL
nexport-0.4.6.dist-info/top_level.txt
nexport-0.4.6.dist-info/RECORD
