Metadata-Version: 2.1
Name: nexport
Version: 0.4.6
Summary: A Python package for exporting the weights and biases of neural networks.
Home-page: https://pypi.org/project/nexport/
Download-URL: https://github.com/JordanWelsman/nexport/tags
Author: Jordan Welsman
Author-email: welsman@lbl.gov
License: LBNL BSD
Keywords: python,neural network,export,import,parameters,weights,biases,layers,neurons
Classifier: Development Status :: 3 - Alpha
Classifier: Intended Audience :: Developers
Classifier: Intended Audience :: Education
Classifier: Intended Audience :: Science/Research
Classifier: License :: OSI Approved :: BSD License
Classifier: Natural Language :: English
Classifier: Operating System :: OS Independent
Classifier: Programming Language :: Python
Classifier: Programming Language :: Python :: 3
Classifier: Programming Language :: Python :: 3.10
Classifier: Programming Language :: Python :: 3.11
Classifier: Topic :: Scientific/Engineering :: Artificial Intelligence
Classifier: Topic :: Software Development :: Libraries :: Python Modules
Classifier: Topic :: Utilities
Requires-Python: >=3.10
License-File: LICENSE.md
Requires-Dist: jutl
Requires-Dist: numpy (<1.24)
